mastercard_spending_pulse-1.0.5.dist-info/DESCRIPTION.rst
mastercard_spending_pulse-1.0.5.dist-info/METADATA
mastercard_spending_pulse-1.0.5.dist-info/RECORD
mastercard_spending_pulse-1.0.5.dist-info/WHEEL
mastercard_spending_pulse-1.0.5.dist-info/metadata.json
mastercard_spending_pulse-1.0.5.dist-info/top_level.txt
mastercardspendingpulse/__init__.py
mastercardspendingpulse/gasweekly.py
mastercardspendingpulse/parameters.py
mastercardspendingpulse/resourceconfig.py
mastercardspendingpulse/spendingpulsereport.py
mastercardspendingpulse/subscription.py
